onionsearch/__init__.py
onionsearch/core.py
onionsearch-1.3.dist-info/LICENSE
onionsearch-1.3.dist-info/METADATA
onionsearch-1.3.dist-info/WHEEL
onionsearch-1.3.dist-info/entry_points.txt
onionsearch-1.3.dist-info/top_level.txt
onionsearch-1.3.dist-info/RECORD
