Metadata-Version: 2.1
Name: onionsearch
Version: 1.3
Summary: OnionSearch is a script that scrapes urls on different .onion search engines.
Home-page: http://github.com/megadose/OnionSearch
Author: megadose
Author-email: UNKNOWN
License: UNKNOWN
Platform: UNKNOWN
Classifier: Programming Language :: Python
Classifier: License :: OSI Approved :: GNU General Public License v3 (GPLv3)
Requires-Dist: PySocks
Requires-Dist: argparse
Requires-Dist: bs4
Requires-Dist: html5lib
Requires-Dist: requests
Requires-Dist: termcolor
Requires-Dist: tqdm
